crystal_ml/config.py
crystal_ml/config.yaml
crystal_ml/pipeline.py
crystal_ml_pipeline-0.5.dist-info/licenses/LICENSE
crystal_ml_pipeline-0.5.dist-info/METADATA
crystal_ml_pipeline-0.5.dist-info/WHEEL
crystal_ml_pipeline-0.5.dist-info/top_level.txt
crystal_ml_pipeline-0.5.dist-info/RECORD
