Metadata-Version: 2.4
Name: crystal_ml_pipeline
Version: 0.5
Summary: End-to-end interpretable binary-classification pipeline
Author-email: Raffaele Mariosa <mraffaele87@gmail.com>
License: The MIT License (MIT)
Project-URL: Homepage, https://github.com/yourusername/crystal-ml
Project-URL: Repository, https://github.com/yourusername/crystal-ml
Classifier: Programming Language :: Python :: 3
Classifier: Programming Language :: Python :: 3.7
Classifier: Programming Language :: Python :: 3.8
Classifier: Programming Language :: Python :: 3.9
Classifier: Programming Language :: Python :: 3.10
Classifier: Programming Language :: Python :: 3.11
Classifier: Programming Language :: Python :: 3.12
Classifier: License :: OSI Approved :: MIT License
Classifier: Operating System :: OS Independent
Requires-Python: <=3.12,>=3.7
License-File: LICENSE
Requires-Dist: pyyaml
Requires-Dist: pandas
Requires-Dist: numpy
Requires-Dist: scikit-learn
Requires-Dist: xgboost
Requires-Dist: imbalanced-learn
Requires-Dist: autogluon
Requires-Dist: openpyxl
Requires-Dist: SupervisedDiscretization
Requires-Dist: gosdt
Requires-Dist: graphviz
Requires-Dist: matplotlib
Requires-Dist: seaborn
Requires-Dist: joblib
Requires-Dist: gurobipy
Dynamic: license-file
